{"errorMessage":false,"texts":[{"username":"PyAlapha","message":"Hey girls!"},{"username":"Scrum Master","message":"Comeon fools! Dont waste your time"},{"username":"PyAlapha","message":"Scrum Master, shut up."},{"username":"hereisdx","message":"Hello, welcome to live chat!dciw weoifnwe woe nwonw oiwefio wniofwe oiwefn woendweion fwoein"},{"username":"PyAlapha","message":"Hey girls!"},{"username":"hereisdx","message":"Actually that is not true"},{"username":"hereisdx2","message":"Hmmm"},{"username":"hereisdx3","message":"Hmmm"},{"username":"hereisdx4","message":"Hmmm"},{"username":"lol","message":"OK"},{"username":"lol","message":"OK"},{"username":"lol","message":"Why twice?"},{"username":"lol","message":"Why twice?"},{"username":"donkey","message":"Imma donkey"},{"username":"donkey","message":"Imma donkey"},{"username":"unagi","message":"hi"},{"username":"unagi","message":"hi"},{"username":"lol","message":"once"},{"username":"lol","message":"once"},{"username":"hereisdx","message":"dude"},{"username":"hereisdx","message":"dude"},{"username":"sdv","message":"sdv"},{"username":"sdv","message":"sdv"},{"username":"sdv","message":"sd"},{"username":"sdv","message":"sd"},{"username":"sd","message":"su"},{"username":"heyBu!","message":"Imma"},{"username":"hereisdx","message":"shadap"},{"username":"sponsor","message":"i am"},{"username":"Anon","message":"not really"},{"username":"anon","message":"papa"},{"username":"anon","message":"please papa"},{"username":"anon","message":"dont hit me"},{"username":"asshole","message":"I am an asshole"},{"username":"arseHole","message":"Yeah"},{"username":"arseHole","message":"I know"},{"username":"arseHole","message":"LOL"},{"username":"arseHole","message":"Right?"},{"username":"hereisdx","message":"I love it"},{"username":"hereisdx","message":"Do you?"},{"username":"hereisdx","message":"Hmmmm"},{"username":"hereisdx","message":"Shit man"},{"username":"hereisdx","message":"ok"},{"username":"hereisdx","message":"lol"},{"username":"hereisdx","message":"Oyeah :-)"},{"username":"hereisdx","message":"Trollolol"},{"username":"hereisdx","message":"TROLOL"},{"username":"hereisdx","message":"Sapm 2019"},{"username":"hereisdx","message":"-------------------------------------"},{"username":"hereisdx","message":"------------------------------------------------------------------------------"},{"username":"hereisdx","message":"---------------------------------------------------------------------------------------------"},{"username":"hereisdx","message":"OOO"},{"username":"hereisdx","message":"LOL"},{"username":"hereisdx","message":"Okkay"}]}